eCHORDopen_post/IPF_V1.py
eCHORDopen_post/Symetry.py
eCHORDopen_post/Xallo.py
echordopen_post-0.1.0.dist-info/LICENSE
echordopen_post-0.1.0.dist-info/METADATA
echordopen_post-0.1.0.dist-info/WHEEL
echordopen_post-0.1.0.dist-info/RECORD
